{
    "$schema": "http://schema.management.azure.com/schemas/2015-01-01/deploymentParameters.json#",
    "contentVersion": "1.0.0.0",
    "parameters": {
        "storageAccountName": {
            "value": "chaisa1"
        },
        "virtualNetworkName": {
            "value": "myVNet"
        },
        "subnetNames": {
            "value": [
                "haProxySubnet",
                "mesosSubnet"
            ]
        },
        "blobContainerNames": {
            "value": [
                "log",
                "share1",
                "share2"
            ]
        },
        "externalSourceIp": {
            "value": "108.7.75.47"
        }
    }
}